{
    "Author": "DOCTOR_STRANGE",
    "name": "FanCode Live Matches API",
    "last_updated": "04:35:06 AM 05-07-2025",
    "headers": {
        "User-Agent": "ReactNativeVideo/7.19.1 (Linux;Android/13) AndroidXMedia3/1.1.1",
        "Referer": "https://fancode.com/"
    },
    "total_matches": 10,
    "live_matches": 1,
    "upcoming_matches": 9,
    "matches": [
        {
            "category": "Golf",
            "title": "Featured Group   Day 2",
            "tournament": "John Deere Classic",
            "short_name": "John Deere Classic",
            "match_id": 130228,
            "status": "COMPLETED",
            "startTime": "04 July 2025 05:45 PM",
            "startDate": "03 July 2025 05:30 AM",
            "endDate": "06 July 2025 11:30 PM",
            "image": "https://www.fancode.com/skillup-uploads/cms-media/John-Deere-Classic_2025_Sporty_Match_card.jpg",
            "image_cdn": {
                "TATAPLAY": "https://images.fancode.com/aig/match/v1/130228_CASACARDS_PARTNER_16_9_1920_1080.png",
                "APP": "https://www.fancode.com/skillup-uploads/cms-media/John-Deere-Classic_2025_Sporty_Match_card.jpg",
                "PLAYBACK": null,
                "CLOUDFARE": "https://d229kpbsb5jevy.cloudfront.net/vffancode2/aig/match/v1/130228_CASACARDS_PARTNER_16_9_1920_1080.png"
            },
            "teams": [
                {
                    "id": 11692,
                    "name": "Featured Group - Day 2",
                    "shortName": "JDC",
                    "logo": "https://d13ir53smqqeyp.cloudfront.net/flags/gl-flags/FC-PGA@2x.png",
                    "flag": "https://d13ir53smqqeyp.cloudfront.net/flags/gl-flags/FC-PGA@2x.png",
                    "color": "#FF0000"
                },
                {
                    "id": 5942,
                    "name": "Location",
                    "shortName": "LOC",
                    "logo": "https://d13ir53smqqeyp.cloudfront.net/flags/gl-flags/FC-LOC@2x.png",
                    "flag": "https://d13ir53smqqeyp.cloudfront.net/flags/gl-flags/FC-LOC@2x.png",
                    "color": "#141414"
                }
            ],
            "language": "BLOODY_SWEET",
            "adfree_stream": null,
            "dai_stream": null,
            "STREAMING_CDN": {
                "language": "BLOODY_SWEET",
                "Primary_Playback_URL": null
            }
        },
        {
            "category": "Golf",
            "title": "Marquee Group   Day 2",
            "tournament": "John Deere Classic",
            "short_name": "John Deere Classic",
            "match_id": 130227,
            "status": "STARTED",
            "startTime": "04 July 2025 05:45 PM",
            "startDate": "03 July 2025 05:30 AM",
            "endDate": "06 July 2025 11:30 PM",
            "image": "https://www.fancode.com/skillup-uploads/cms-media/John-Deere-Classic_2025_Sporty_Match_card.jpg",
            "image_cdn": {
                "TATAPLAY": "https://images.fancode.com/aig/match/v1/130227_CASACARDS_PARTNER_16_9_1920_1080.png",
                "APP": "https://www.fancode.com/skillup-uploads/cms-media/John-Deere-Classic_2025_Sporty_Match_card.jpg",
                "PLAYBACK": "https://www.fancode.com/skillup-uploads/cms-media/John-Deere-Classic_2025_match-card_1751540737472.jpg",
                "CLOUDFARE": "https://d229kpbsb5jevy.cloudfront.net/vffancode2/aig/match/v1/130227_CASACARDS_PARTNER_16_9_1920_1080.png"
            },
            "teams": [
                {
                    "id": 11692,
                    "name": "Marquee Group - Day 2",
                    "shortName": "JDC",
                    "logo": "https://d13ir53smqqeyp.cloudfront.net/flags/gl-flags/FC-PGA@2x.png",
                    "flag": "https://d13ir53smqqeyp.cloudfront.net/flags/gl-flags/FC-PGA@2x.png",
                    "color": "#FF0000"
                },
                {
                    "id": 5942,
                    "name": "Location",
                    "shortName": "LOC",
                    "logo": "https://d13ir53smqqeyp.cloudfront.net/flags/gl-flags/FC-LOC@2x.png",
                    "flag": "https://d13ir53smqqeyp.cloudfront.net/flags/gl-flags/FC-LOC@2x.png",
                    "color": "#141414"
                }
            ],
            "language": "ENGLISH",
            "adfree_stream": "https://in-mc-fdlive.fancode.com/mumbai/130227_english_hls_87064ta-di_h264/index.m3u8",
            "dai_stream": "https://dai.google.com/linear/hls/event/IbG6AVs7TPOPIyorQpOLmg/master.m3u8",
            "STREAMING_CDN": {
                "Primary_Playback_URL": "https://in-mc-fdlive.fancode.com/mumbai/130227_english_hls_87064ta-di_h264/index.m3u8",
                "fancode_cdn": "https://in-mc-fdlive.fancode.com/mumbai/130227_english_hls_87064ta-di_h264/index.m3u8",
                "dai_google_cdn": "https://dai.google.com/linear/hls/event/IbG6AVs7TPOPIyorQpOLmg/master.m3u8",
                "cloudfront_cdn": "Unavailable",
                "language": "ENGLISH"
            }
        },
        {
            "category": "Cricket",
            "title": "England Women Vs India Women",
            "tournament": "India Women tour of England, 2025",
            "short_name": "ENG-W vs IND-W",
            "match_id": 128742,
            "status": "COMPLETED",
            "startTime": "04 July 2025 11:05 PM",
            "startDate": "28 June 2025 05:30 AM",
            "endDate": "22 July 2025 05:30 AM",
            "image": "https://www.fancode.com/skillup-uploads/cms-media/IND-Vs-ENG_T-20-Series_2025_Sporty_Match_card.jpg",
            "image_cdn": {
                "TATAPLAY": "https://images.fancode.com/aig/match/v1/128742_CASACARDS_PARTNER_16_9_1920_1080.png",
                "APP": "https://www.fancode.com/skillup-uploads/cms-media/IND-Vs-ENG_T-20-Series_2025_Sporty_Match_card.jpg",
                "PLAYBACK": null,
                "CLOUDFARE": "https://d229kpbsb5jevy.cloudfront.net/vffancode2/aig/match/v1/128742_CASACARDS_PARTNER_16_9_1920_1080.png"
            },
            "teams": [
                {
                    "id": 646,
                    "name": "England Women",
                    "shortName": "EN-W",
                    "logo": "https://d13ir53smqqeyp.cloudfront.net/flags/cr-flags/FC-ENG@2x.png",
                    "flag": "https://d13ir53smqqeyp.cloudfront.net/flags/cr-flags/FC-ENG@2x.png",
                    "color": "#3c9ae8"
                },
                {
                    "id": 710,
                    "name": "India Women",
                    "shortName": "IN-W",
                    "logo": "https://d13ir53smqqeyp.cloudfront.net/flags/cr-flags/FC-IND@2x.png",
                    "flag": "https://d13ir53smqqeyp.cloudfront.net/flags/cr-flags/FC-IND@2x.png",
                    "color": "#0f60de"
                }
            ],
            "language": "BLOODY_SWEET",
            "adfree_stream": null,
            "dai_stream": null,
            "STREAMING_CDN": {
                "language": "BLOODY_SWEET",
                "Primary_Playback_URL": null
            }
        },
        {
            "category": "Cricket",
            "title": "West Indies Vs Australia",
            "tournament": "Australia Tour of West Indies, 2025",
            "short_name": "WI vs AUS",
            "match_id": 127551,
            "status": "PAUSED",
            "startTime": "03 July 2025 07:15 PM",
            "startDate": "25 June 2025 05:30 AM",
            "endDate": "29 July 2025 05:30 AM",
            "image": "https://www.fancode.com/skillup-uploads/cms-media/WI_vs_AUS_2025_Sporty_match-card.jpg",
            "image_cdn": {
                "TATAPLAY": "https://images.fancode.com/aig/match/v1/127551_CASACARDS_PARTNER_16_9_1920_1080.png",
                "APP": "https://www.fancode.com/skillup-uploads/cms-media/WI_vs_AUS_2025_Sporty_match-card.jpg",
                "PLAYBACK": null,
                "CLOUDFARE": "https://d229kpbsb5jevy.cloudfront.net/vffancode2/aig/match/v1/127551_CASACARDS_PARTNER_16_9_1920_1080.png"
            },
            "teams": [
                {
                    "id": 260,
                    "name": "West Indies",
                    "shortName": "WI",
                    "logo": "https://d13ir53smqqeyp.cloudfront.net/flags/cr-flags/FC-WIN@2x.png",
                    "flag": "https://d13ir53smqqeyp.cloudfront.net/flags/cr-flags/FC-WIN@2x.png",
                    "color": "#7B0041"
                },
                {
                    "id": 13,
                    "name": "Australia",
                    "shortName": "AUS",
                    "logo": "https://d13ir53smqqeyp.cloudfront.net/flags/cr-flags/FC-AUS@2x.png",
                    "flag": "https://d13ir53smqqeyp.cloudfront.net/flags/cr-flags/FC-AUS@2x.png",
                    "color": "#002695"
                }
            ],
            "language": "BLOODY_SWEET",
            "adfree_stream": null,
            "dai_stream": null,
            "STREAMING_CDN": {
                "language": "BLOODY_SWEET",
                "Primary_Playback_URL": null
            }
        },
        {
            "category": "Cricket",
            "title": "Sri Lanka Vs Bangladesh",
            "tournament": "Bangladesh tour of Sri Lanka, 2025",
            "short_name": "SL vs BAN",
            "match_id": 128429,
            "status": "NOT_STARTED",
            "startTime": "05 July 2025 02:30 PM",
            "startDate": "17 June 2025 05:30 AM",
            "endDate": "16 July 2025 05:30 AM",
            "image": "https://www.fancode.com/skillup-uploads/cms-media/Bangladesh-Tour-of-Sri-Lanka,-ODIs-Sporrty-match-card.png",
            "image_cdn": {
                "TATAPLAY": "https://images.fancode.com/aig/match/v1/128429_CASACARDS_PARTNER_16_9_1920_1080.png",
                "APP": "https://www.fancode.com/skillup-uploads/cms-media/Bangladesh-Tour-of-Sri-Lanka,-ODIs-Sporrty-match-card.png",
                "PLAYBACK": null,
                "CLOUDFARE": "https://d229kpbsb5jevy.cloudfront.net/vffancode2/aig/match/v1/128429_CASACARDS_PARTNER_16_9_1920_1080.png"
            },
            "teams": [
                {
                    "id": 44,
                    "name": "Sri Lanka",
                    "shortName": "SL",
                    "logo": "https://d13ir53smqqeyp.cloudfront.net/flags/cr-flags/FC-SRL@2x.png",
                    "flag": "https://d13ir53smqqeyp.cloudfront.net/flags/cr-flags/FC-SRL@2x.png",
                    "color": "#164fad"
                },
                {
                    "id": 25,
                    "name": "Bangladesh",
                    "shortName": "BAN",
                    "logo": "https://d13ir53smqqeyp.cloudfront.net/flags/cr-flags/FC-BAN@2x.png",
                    "flag": "https://d13ir53smqqeyp.cloudfront.net/flags/cr-flags/FC-BAN@2x.png",
                    "color": "#397b46"
                }
            ],
            "language": "BLOODY_SWEET",
            "adfree_stream": null,
            "dai_stream": null,
            "STREAMING_CDN": {
                "language": "BLOODY_SWEET",
                "Primary_Playback_URL": null
            }
        },
        {
            "category": "Cricket",
            "title": "Sussex Vs Hampshire",
            "tournament": "Vitality Blast T20, 2025",
            "short_name": "Vitality Blast T20",
            "match_id": 125965,
            "status": "NOT_STARTED",
            "startTime": "05 July 2025 11:30 PM",
            "startDate": "29 May 2025 05:30 AM",
            "endDate": "13 September 2025 05:30 AM",
            "image": "https://www.fancode.com/skillup-uploads/cms-media/125965_5207_SUS_HAM_fc-App.jpg",
            "image_cdn": {
                "TATAPLAY": "https://images.fancode.com/aig/match/v1/125965_CASACARDS_PARTNER_16_9_1920_1080.png",
                "APP": "https://www.fancode.com/skillup-uploads/cms-media/125965_5207_SUS_HAM_fc-App.jpg",
                "PLAYBACK": null,
                "CLOUDFARE": "https://d229kpbsb5jevy.cloudfront.net/vffancode2/aig/match/v1/125965_CASACARDS_PARTNER_16_9_1920_1080.png"
            },
            "teams": [
                {
                    "id": 283,
                    "name": "Sussex",
                    "shortName": "SUS",
                    "logo": "https://d13ir53smqqeyp.cloudfront.net/flags/cr-flags/FC-SUS@2x.png",
                    "flag": "https://d13ir53smqqeyp.cloudfront.net/flags/cr-flags/FC-SUS@2x.png",
                    "color": "#256caf"
                },
                {
                    "id": 308,
                    "name": "Hampshire",
                    "shortName": "HAM",
                    "logo": "https://d13ir53smqqeyp.cloudfront.net/flags/cr-flags/FC-HAMP@2x.png",
                    "flag": "https://d13ir53smqqeyp.cloudfront.net/flags/cr-flags/FC-HAMP@2x.png",
                    "color": "#9b7614"
                }
            ],
            "language": "BLOODY_SWEET",
            "adfree_stream": null,
            "dai_stream": null,
            "STREAMING_CDN": {
                "language": "BLOODY_SWEET",
                "Primary_Playback_URL": null
            }
        },
        {
            "category": "Football",
            "title": "Wales Women Vs Netherlands Women",
            "tournament": "UEFA Women's EURO 2025",
            "short_name": "Women's Euro",
            "match_id": 123351,
            "status": "NOT_STARTED",
            "startTime": "05 July 2025 09:30 PM",
            "startDate": "02 July 2025 05:30 AM",
            "endDate": "27 July 2025 11:30 PM",
            "image": "https://www.fancode.com/skillup-uploads/cms-media/123351_5107_WAL-W_NED-W_fc-app.jpg",
            "image_cdn": {
                "TATAPLAY": "https://images.fancode.com/aig/match/v1/123351_CASACARDS_PARTNER_16_9_1920_1080.png",
                "APP": "https://www.fancode.com/skillup-uploads/cms-media/123351_5107_WAL-W_NED-W_fc-app.jpg",
                "PLAYBACK": null,
                "CLOUDFARE": "https://d229kpbsb5jevy.cloudfront.net/vffancode2/aig/match/v1/123351_CASACARDS_PARTNER_16_9_1920_1080.png"
            },
            "teams": [
                {
                    "id": 8820,
                    "name": "Wales Women",
                    "shortName": "WAL-W",
                    "logo": "https://d13ir53smqqeyp.cloudfront.net/flags/ft-flags/WAL-FT1@2x.png",
                    "flag": "https://d13ir53smqqeyp.cloudfront.net/flags/ft-flags/WAL-FT1@2x.png",
                    "color": "#dd717a"
                },
                {
                    "id": 1253,
                    "name": "Netherlands Women",
                    "shortName": "NED-W",
                    "logo": "https://d13ir53smqqeyp.cloudfront.net/flags/ft-flags/FC-NED@2x.png",
                    "flag": "https://d13ir53smqqeyp.cloudfront.net/flags/ft-flags/FC-NED@2x.png",
                    "color": "#fc8200"
                }
            ],
            "language": "BLOODY_SWEET",
            "adfree_stream": null,
            "dai_stream": null,
            "STREAMING_CDN": {
                "language": "BLOODY_SWEET",
                "Primary_Playback_URL": null
            }
        },
        {
            "category": "Football",
            "title": "France Women Vs England Women",
            "tournament": "UEFA Women's EURO 2025",
            "short_name": "Women's Euro",
            "match_id": 123350,
            "status": "NOT_STARTED",
            "startTime": "06 July 2025 12:30 AM",
            "startDate": "02 July 2025 05:30 AM",
            "endDate": "27 July 2025 11:30 PM",
            "image": "https://www.fancode.com/skillup-uploads/cms-media/123350_5107_FRA-W_ENG-W_fc-app.jpg",
            "image_cdn": {
                "TATAPLAY": "https://images.fancode.com/aig/match/v1/123350_CASACARDS_PARTNER_16_9_1920_1080.png",
                "APP": "https://www.fancode.com/skillup-uploads/cms-media/123350_5107_FRA-W_ENG-W_fc-app.jpg",
                "PLAYBACK": null,
                "CLOUDFARE": "https://d229kpbsb5jevy.cloudfront.net/vffancode2/aig/match/v1/123350_CASACARDS_PARTNER_16_9_1920_1080.png"
            },
            "teams": [
                {
                    "id": 1256,
                    "name": "France Women",
                    "shortName": "FRA-W",
                    "logo": "https://d13ir53smqqeyp.cloudfront.net/flags/ft-flags/FC-FRC@2x.png",
                    "flag": "https://d13ir53smqqeyp.cloudfront.net/flags/ft-flags/FC-FRC@2x.png",
                    "color": "#112d64"
                },
                {
                    "id": 1251,
                    "name": "England Women",
                    "shortName": "ENG-W",
                    "logo": "https://d13ir53smqqeyp.cloudfront.net/flags/ft-flags/FC-ENGL@2x.png",
                    "flag": "https://d13ir53smqqeyp.cloudfront.net/flags/ft-flags/FC-ENGL@2x.png",
                    "color": "#2257c1"
                }
            ],
            "language": "BLOODY_SWEET",
            "adfree_stream": null,
            "dai_stream": null,
            "STREAMING_CDN": {
                "language": "BLOODY_SWEET",
                "Primary_Playback_URL": null
            }
        },
        {
            "category": "Formula 1",
            "title": "Practice 3",
            "tournament": "F1 QATAR AIRWAYS BRITISH GRAND PRIX 2025",
            "short_name": "British GP",
            "match_id": 118438,
            "status": "NOT_STARTED",
            "startTime": "05 July 2025 04:00 PM",
            "startDate": "04 July 2025 05:30 AM",
            "endDate": "06 July 2025 11:45 PM",
            "image": "https://www.fancode.com/skillup-uploads/cms-media/British_GP_F1_Practice_3_Match_card.jpg",
            "image_cdn": {
                "TATAPLAY": "https://images.fancode.com/aig/match/v1/118438_CASACARDS_PARTNER_16_9_1920_1080.png",
                "APP": "https://www.fancode.com/skillup-uploads/cms-media/British_GP_F1_Practice_3_Match_card.jpg",
                "PLAYBACK": null,
                "CLOUDFARE": "https://d229kpbsb5jevy.cloudfront.net/vffancode2/aig/match/v1/118438_CASACARDS_PARTNER_16_9_1920_1080.png"
            },
            "teams": [
                {
                    "id": 8202,
                    "name": "Practice 3",
                    "shortName": "P3",
                    "logo": "https://d13ir53smqqeyp.cloudfront.net/flags/f1-flags/FC-FR5@2x.png",
                    "flag": "https://d13ir53smqqeyp.cloudfront.net/flags/f1-flags/FC-FR5@2x.png",
                    "color": "#EE0000"
                },
                {
                    "id": 8199,
                    "name": "Location",
                    "shortName": "LOC",
                    "logo": "https://d13ir53smqqeyp.cloudfront.net/flags/f1-flags/FC-LOT@2x.png",
                    "flag": "https://d13ir53smqqeyp.cloudfront.net/flags/f1-flags/FC-LOT@2x.png",
                    "color": "#141414"
                }
            ],
            "language": "BLOODY_SWEET",
            "adfree_stream": null,
            "dai_stream": null,
            "STREAMING_CDN": {
                "language": "BLOODY_SWEET",
                "Primary_Playback_URL": null
            }
        },
        {
            "category": "Golf",
            "title": "Featured Holes   Day 2",
            "tournament": "John Deere Classic",
            "short_name": "John Deere Classic",
            "match_id": 130226,
            "status": "COMPLETED",
            "startTime": "04 July 2025 05:45 PM",
            "startDate": "03 July 2025 05:30 AM",
            "endDate": "06 July 2025 11:30 PM",
            "image": "https://www.fancode.com/skillup-uploads/cms-media/John-Deere-Classic_2025_match-card_1751540737472.jpg",
            "image_cdn": {
                "TATAPLAY": "https://images.fancode.com/aig/match/v1/130226_CASACARDS_PARTNER_16_9_1920_1080.png",
                "APP": "https://www.fancode.com/skillup-uploads/cms-media/John-Deere-Classic_2025_match-card_1751540737472.jpg",
                "PLAYBACK": null,
                "CLOUDFARE": "https://d229kpbsb5jevy.cloudfront.net/vffancode2/aig/match/v1/130226_CASACARDS_PARTNER_16_9_1920_1080.png"
            },
            "teams": [
                {
                    "id": 11692,
                    "name": "Featured Holes - Day 2",
                    "shortName": "JDC",
                    "logo": "https://d13ir53smqqeyp.cloudfront.net/flags/gl-flags/FC-PGA@2x.png",
                    "flag": "https://d13ir53smqqeyp.cloudfront.net/flags/gl-flags/FC-PGA@2x.png",
                    "color": "#FF0000"
                },
                {
                    "id": 5942,
                    "name": "Location",
                    "shortName": "LOC",
                    "logo": "https://d13ir53smqqeyp.cloudfront.net/flags/gl-flags/FC-LOC@2x.png",
                    "flag": "https://d13ir53smqqeyp.cloudfront.net/flags/gl-flags/FC-LOC@2x.png",
                    "color": "#141414"
                }
            ],
            "language": "BLOODY_SWEET",
            "adfree_stream": null,
            "dai_stream": null,
            "STREAMING_CDN": {
                "language": "BLOODY_SWEET",
                "Primary_Playback_URL": null
            }
        }
    ]
}